barrier/__init__.py
barrier/app.py
barrier/configure.py
barrier/wsgi.py
barrier-0.2.2.dist-info/entry_points.txt
barrier-0.2.2.dist-info/LICENSE
barrier-0.2.2.dist-info/WHEEL
barrier-0.2.2.dist-info/METADATA
barrier-0.2.2.dist-info/RECORD
