Metadata-Version: 2.1
Name: barrier
Version: 0.2.2
Summary: Serve static files safely behind OpenIDConnect-compatible authentication (i.e. Okta)
Home-page: https://github.com/gadventures/barrier
License: MIT
Author: Matthew de Verteuil
Author-email: mdeverteuil@gadventures.com
Requires-Python: >=3.7,<4.0
Classifier: License :: OSI Approved :: MIT License
Classifier: Programming Language :: Python :: 3
Classifier: Programming Language :: Python :: 3.7
Requires-Dist: Flask (>=1.1,<2.0)
Requires-Dist: flask-oidc (>=1.4,<2.0)
Requires-Dist: gunicorn (>=19.9,<20.0)
Requires-Dist: poetry-version (>=0.1.3,<0.2.0)
Project-URL: Repository, https://github.com/gadventures/barrier
